final/src/cut_driver.v
// Team number: 5    
// Author: Edwin Chen
// 
// Create Date: 01/14/2018
// Project Name: Kitchen's helper
// Module Name: cut_driver
// Target Devices: DE2-115

module cut_driver#(
    parameter define_speed = 10
)(
    input       clk,
    input       rst_n,
    
    // I/O with controller
    input       cut_i,
    output      cut_end_o,
    
    // I/O with motor
    output [3:0]signal_o
);
    wire new_clk;
    
    clock_div0 #(
        .define_speed(define_speed)
    )clock_div0(
		.clk        (clk),
		.rst_n      (rst_n),
		.new_clk    (new_clk) 
    );
    
    cutting_step_driver cutting_step_driver0(
		.clk        (new_clk),
		.rst_n      (rst_n),
		.en_i       (cut_i),
		.cut_end_o  (cut_end_o), 
		.signal_o   (signal_o)
    );

endmodule


// Description: This is a clock divider. It takes the system clock 
// and divides that down to a slower clock. It counts at the rate of the 
// system clock to define_speed and toggles the output clock signal. 
module clock_div0#(
  parameter define_speed = 10 // Unit: ms 
)
(
    input clk,
    input rst_n,
    output reg new_clk
);
    
    // The constant that defines the clock speed. 
    // Since the system clock is 50MHZ, 
    // define_speed = (2*desired_clock_frequency)/50MHz
    // localparam desired_clock_freq = 50Hz
    localparam define_half_cycle = 25000*define_speed-1;
    
    // Count value that counts to define_speed
    reg [31:0] count;
    
    always @ (posedge clk or negedge rst_n) begin
        // When rst is low set count and new_clk to 0
        if (!rst_n) begin 
            count   <= 32'b0;   
            new_clk <= 1'b0;            
        end
        // When the count has reached the constant
        // reset count and toggle the output clock
        else if (count == define_half_cycle)
        begin
            count   <= 32'b0;
            new_clk <= ~new_clk;
        end
        // increment the clock and keep the output clock
        // the same when the constant hasn't been reached        
        else
        begin
            count   <= count + 1'b1;
            new_clk <= new_clk;
        end
    end
    
endmodule

// Description: This is the state machine that drives
// the output to the PmodSTEP. It alternates one of four pins being
// high at a rate set by the clock divider. 
module cutting_step_driver#(
    parameter define_speed = 10 // unit: ms, which means 10ms trun 0.9 degree
)
(
    input   clk,    // clk from clock driver
    input   rst_n,
    
    // I/O with controller
    input   en_i,    // enable motor to rotate
    output  cut_end_o,
    
    // I/O with step motor
    output  [3:0] signal_o
    );
    
    // localparam define_clock_cycle = 50000*define_speed;    
    localparam define_clock_cycle = 5*define_speed;   
    
    // 4  3  2 1 -th bit
    // B' A' B A
    // clockwise
    // 4->3->2->1
    // counter-clockwise
    // 1->2->3->4
    localparam sig0     = 4'b0;
    // "Two phase mode"
    localparam sig1     = 4'b0011; // 3
    localparam sig2     = 4'b0110; // 6
    localparam sig3     = 4'b1100; // 12
    localparam sig4     = 4'b1001; // 9
    
    
    reg [3:0]   state, nxt_state;

    reg         cut_end, nxt_cut_end;
    reg [3:0]   signal, nxt_signal;
    
    reg         direction, nxt_direction;
    reg [31:0]  clk_cnt, nxt_clk_cnt; // 0~define_clock_cycle, cnt how many clk cycles
    reg [6:0]   cnt, nxt_cnt; // 0~100 each cnt represents 0.9 degree

// =========== Finite State Machine ============
 
    always @ (posedge clk or negedge rst_n) begin
        if (!rst_n)
            state <= sig0;
        else 
            state <= nxt_state;
    end

    always @ (*) begin
        case(state)
        sig0: begin
            if (en_i == 1'b1)
                nxt_state = sig1;
            else 
                nxt_state = sig0;
        end 
        sig1: begin
            if (direction == 1'b0 && en_i == 1'b1)
                nxt_state = sig4;
            else if (direction == 1'b1 && en_i == 1'b1)
                nxt_state = sig2;
            else 
                nxt_state = sig0;
        end
        sig2: begin
            if (direction == 1'b0 && en_i == 1'b1)
                nxt_state = sig1;
            else if (direction == 1'b1 && en_i == 1'b1)
                nxt_state = sig3;
            else 
                nxt_state = sig0;
        end 
        sig3: begin
            if (direction == 1'b0 && en_i == 1'b1)
                nxt_state = sig2;
            else if (direction == 1'b1 && en_i == 1'b1)
                nxt_state = sig4;
            else 
                nxt_state = sig0;
        end 
        // If the state is sig4, the state where
        // the fourth signal is held high.
        sig4: begin
            if (direction == 1'b0 && en_i == 1'b1)
                nxt_state = sig3;
            else if (direction == 1'b1 && en_i == 1'b1)
                nxt_state = sig1;
            else 
                nxt_state = sig0;
        end  
        default:
            nxt_state = sig0; 
        endcase
    end 
    
//============= Combitional LOgic ===============
    assign signal_o     = signal;
    assign cut_end_o    = cut_end;    
    
    // Output Logic, Depending on the state, output signal has a different value.     
    always @ (*) begin
        if (state == sig4)
            nxt_signal = sig4;
        else 
        if (state == sig3)
            nxt_signal = sig3;
        else 
        if (state == sig2)
            nxt_signal = sig2;  
        else 
        if (state == sig1)
            nxt_signal = sig1;
        else
            nxt_signal = 0;
    end
    
    always@(*) begin
        if(clk_cnt == define_clock_cycle)
            nxt_clk_cnt  = 0;
        else
        if(en_i) 
            nxt_clk_cnt  = clk_cnt + 1'b1;
        else 
            nxt_clk_cnt  = clk_cnt;  
    end
    
    // cnt && direction
    always@(*) begin
        if(cnt == 7'd100) begin // 90 / 0.9 = 100
            nxt_cnt         = 0;
            nxt_direction   = direction + 1'b1;
        end
        else
        if(clk_cnt == define_clock_cycle) begin
            nxt_cnt         = cnt + 1'b1;
            nxt_direction   = direction;
        end
        else begin
            nxt_cnt         = cnt;  
            nxt_direction   = direction; 
        end
    end
    
    // cut_end
    always@(*) begin
        if(cnt == 7'd100 && direction == 1) 
            nxt_cut_end     = 1;
        else
            nxt_cut_end     = 0;
    end
    


//=========== Sequential Logic =============    
    always @ (posedge clk or negedge rst_n) begin
        if(!rst_n) begin
            signal      <= 0;  
            cut_end     <= 0;
            direction   <= 0;
            clk_cnt     <= 0;
            cnt         <= 0;
        end
        else begin
            signal      <= nxt_signal;  
            cut_end     <= nxt_cut_end;
            direction   <= nxt_direction;
            clk_cnt     <= nxt_clk_cnt;
            cnt         <= nxt_cnt;        
        end
    end
endmodule

final/testbench/cut_driver_tb.v
`timescale 1ns/100ps
`define CYCLE  20.0
`define H_CYCLE (`CYCLE/2)
`include   "../src/cut_driver.v"

module test_cut_controller_driver;

    localparam define_speed = 0.0002; // ms 200ns

/*=============== reg/wire declaration =============*/
	reg         clk;
    reg         rst_n;
    
    // I/O with controller
    reg         cut_i;
    wire        cut_end_o;
    
    // I/O with motor
    wire [3:0]  signal_o;

/*================ module instantiation ================*/

	cut_driver #(
        .define_speed(define_speed)
    )DUT (
		.clk        (clk),
		.rst_n      (rst_n),
		.cut_i      (cut_i),
		.cut_end_o  (cut_end_o),
		.signal_o   (signal_o)
	);

	// Dump waveform file
	initial begin
		$dumpfile("cut_driver.vcd");
		$dumpvars;			
	end
	
	// clock signal settings
	initial begin
        clk = 1'b0;
        forever #(`H_CYCLE) clk = ~clk;
    end

	// test_cut_controller_driver
	initial begin               
        rst_n = 0;
		#(`CYCLE*1.2);
		rst_n = 1;		
        #(`CYCLE*2); 
        
        // cut_i
        cut_i = 1;        	
        #(`CYCLE*5);
        cut_i = 0;  	
        #(`CYCLE*2); 
        cut_i = 1;         
        
        @(cut_end_o) $display("\nfinish\n");
		$finish;
	end
    
    // abort if the design cannot halt
    initial begin
        #(`CYCLE * 1000000 );
        $display( "\n" );
        $display( "Your design doesn't finish all operations in reasonable interval." );
        $display( "Terminated at: ", $time, " ns" );
        $display( "\n" );
        $finish;
    end
 
endmodule

final/testbench/cut_controller_driver.vcd
$date
	Tue Jan 16 20:22:44 2018
$end
$version
	Icarus Verilog
$end
$timescale
	100ps
$end
$scope module test_cut_controller_driver $end
$var wire 4 ! signal_o [3:0] $end
$var wire 1 " cut_end_o $end
$var reg 1 # clk $end
$var reg 1 $ cut_i $end
$var reg 1 % rst_n $end
$scope module DUT $end
$var wire 1 # clk $end
$var wire 1 $ cut_i $end
$var wire 1 % rst_n $end
$var wire 4 & signal_o [3:0] $end
$var wire 1 ' new_clk $end
$var wire 1 " cut_end_o $end
$scope module clock_div0 $end
$var wire 1 # clk $end
$var wire 1 % rst_n $end
$var reg 32 ( count [31:0] $end
$var reg 1 ' new_clk $end
$upscope $end
$scope module cutting_step_driver0 $end
$var wire 1 ' clk $end
$var wire 1 " cut_end_o $end
$var wire 1 $ en_i $end
$var wire 1 % rst_n $end
$var wire 4 ) signal_o [3:0] $end
$var reg 32 * clk_cnt [31:0] $end
$var reg 7 + cnt [6:0] $end
$var reg 1 , cut_end $end
$var reg 1 - direction $end
$var reg 32 . nxt_clk_cnt [31:0] $end
$var reg 7 / nxt_cnt [6:0] $end
$var reg 1 0 nxt_cut_end $end
$var reg 1 1 nxt_direction $end
$var reg 4 2 nxt_signal [3:0] $end
$var reg 4 3 nxt_state [3:0] $end
$var reg 4 4 signal [3:0] $end
$var reg 4 5 state [3:0] $end
$upscope $end
$upscope $end
$upscope $end
$enddefinitions $end
#0
$dumpvars
b0 5
b0 4
b0 3
b0 2
01
00
b0 /
b0 .
0-
0,
b0 +
b0 *
b0 )
b0 (
0'
b0 &
0%
x$
0#
0"
b0 !
$end
#100
1#
#200
0#
#240
1%
#300
b1 (
1#
#400
0#
#500
b10 (
1#
#600
0#
#640
b1 .
b11 3
1$
#700
b11 (
1#
#800
0#
#900
b100 (
1#
#1000
0#
#1100
b10 .
b11 2
b1001 3
b1 *
b11 5
1'
b0 (
1#
#1200
0#
#1300
b1 (
1#
#1400
0#
#1500
b10 (
1#
#1600
0#
#1640
b1 .
b0 3
0$
#1700
b11 (
1#
#1800
0#
#1900
b100 (
1#
#2000
0#
#2040
b10 .
b1001 3
1$
#2100
0'
b0 (
1#
#2200
0#
#2300
b1 (
1#
#2400
0#
#2500
b10 (
1#
#2600
0#
#2700
b11 (
1#
#2800
0#
#2900
b100 (
1#
#3000
0#
#3100
b1001 2
b1100 3
b11 .
b1001 5
b10 *
b11 !
b11 &
b11 )
b11 4
1'
b0 (
1#
#3200
0#
#3300
b1 (
1#
#3400
0#
#3500
b10 (
1#
#3600
0#
#3700
b11 (
1#
#3800
0#
#3900
b100 (
1#
#4000
0#
#4100
0'
b0 (
1#
#4200
0#
#4300
b1 (
1#
#4400
0#
#4500
b10 (
1#
#4600
0#
#4700
b11 (
1#
#4800
0#
#4900
b100 (
1#
#5000
0#
#5100
b100 .
b1100 2
b110 3
b11 *
b1001 !
b1001 &
b1001 )
b1001 4
b1100 5
1'
b0 (
1#
#5200
0#
#5300
b1 (
1#
#5400
0#
#5500
b10 (
1#
#5600
0#
#5700
b11 (
1#
#5800
0#
#5900
b100 (
1#
#6000
0#
#6100
0'
b0 (
1#
#6200
0#
#6300
b1 (
1#
#6400
0#
#6500
b10 (
1#
#6600
0#
#6700
b11 (
1#
#6800
0#
#6900
b100 (
1#
#7000
0#
#7100
b110 2
b11 3
b101 .
b110 5
b100 *
b1100 !
b1100 &
b1100 )
b1100 4
1'
b0 (
1#
#7200
0#
#7300
b1 (
1#
#7400
0#
#7500
b10 (
1#
#7600
0#
#7700
b11 (
1#
#7800
0#
#7900
b100 (
1#
#8000
0#
#8100
0'
b0 (
1#
#8200
0#
#8300
b1 (
1#
#8400
0#
#8500
b10 (
1#
#8600
0#
#8700
b11 (
1#
#8800
0#
#8900
b100 (
1#
#9000
0#
#9100
b110 .
b11 2
b1001 3
b101 *
b110 !
b110 &
b110 )
b110 4
b11 5
1'
b0 (
1#
#9200
0#
#9300
b1 (
1#
#9400
0#
#9500
b10 (
1#
#9600
0#
#9700
b11 (
1#
#9800
0#
#9900
b100 (
1#
#10000
0#
#10100
0'
b0 (
1#
#10200
0#
#10300
b1 (
1#
#10400
0#
#10500
b10 (
1#
#10600
0#
#10700
b11 (
1#
#10800
0#
#10900
b100 (
1#
#11000
0#
#11100
b1001 2
b1100 3
b111 .
b1001 5
b110 *
b11 !
b11 &
b11 )
b11 4
1'
b0 (
1#
#11200
0#
#11300
b1 (
1#
#11400
0#
#11500
b10 (
1#
#11600
0#
#11700
b11 (
1#
#11800
0#
#11900
b100 (
1#
#12000
0#
#12100
0'
b0 (
1#
#12200
0#
#12300
b1 (
1#
#12400
0#
#12500
b10 (
1#
#12600
0#
#12700
b11 (
1#
#12800
0#
#12900
b100 (
1#
#13000
0#
#13100
b1000 .
b1100 2
b110 3
b111 *
b1001 !
b1001 &
b1001 )
b1001 4
b1100 5
1'
b0 (
1#
#13200
0#
#13300
b1 (
1#
#13400
0#
#13500
b10 (
1#
#13600
0#
#13700
b11 (
1#
#13800
0#
#13900
b100 (
1#
#14000
0#
#14100
0'
b0 (
1#
#14200
0#
#14300
b1 (
1#
#14400
0#
#14500
b10 (
1#
#14600
0#
#14700
b11 (
1#
#14800
0#
#14900
b100 (
1#
#15000
0#
#15100
b110 2
b11 3
b1001 .
b110 5
b1000 *
b1100 !
b1100 &
b1100 )
b1100 4
1'
b0 (
1#
#15200
0#
#15300
b1 (
1#
#15400
0#
#15500
b10 (
1#
#15600
0#
#15700
b11 (
1#
#15800
0#
#15900
b100 (
1#
#16000
0#
#16100
0'
b0 (
1#
#16200
0#
#16300
b1 (
1#
#16400
0#
#16500
b10 (
1#
#16600
0#
#16700
b11 (
1#
#16800
0#
#16900
b100 (
1#
#17000
0#
#17100
b1010 .
b11 2
b1001 3
b1001 *
b110 !
b110 &
b110 )
b110 4
b11 5
1'
b0 (
1#
#17200
0#
#17300
b1 (
1#
#17400
0#
#17500
b10 (
1#
#17600
0#
#17700
b11 (
1#
#17800
0#
#17900
b100 (
1#
#18000
0#
#18100
0'
b0 (
1#
#18200
0#
#18300
b1 (
1#
#18400
0#
#18500
b10 (
1#
#18600
0#
#18700
b11 (
1#
#18800
0#
#18900
b100 (
1#
#19000
0#
#19100
b1001 2
b1100 3
b1011 .
b1001 5
b1010 *
b11 !
b11 &
b11 )
b11 4
1'
b0 (
1#
#19200
0#
#19300
b1 (
1#
#19400
0#
#19500
b10 (
1#
#19600
0#
#19700
b11 (
1#
#19800
0#
#19900
b100 (
1#
#20000
0#
#20100
0'
b0 (
1#
#20200
0#
#20300
b1 (
1#
#20400
0#
#20500
b10 (
1#
#20600
0#
#20700
b11 (
1#
#20800
0#
#20900
b100 (
1#
#21000
0#
#21100
b1100 .
b1100 2
b110 3
b1011 *
b1001 !
b1001 &
b1001 )
b1001 4
b1100 5
1'
b0 (
1#
#21200
0#
#21300
b1 (
1#
#21400
0#
#21500
b10 (
1#
#21600
0#
#21700
b11 (
1#
#21800
0#
#21900
b100 (
1#
#22000
0#
#22100
0'
b0 (
1#
#22200
0#
#22300
b1 (
1#
#22400
0#
#22500
b10 (
1#
#22600
0#
#22700
b11 (
1#
#22800
0#
#22900
b100 (
1#
#23000
0#
#23100
b110 2
b11 3
b1101 .
b110 5
b1100 *
b1100 !
b1100 &
b1100 )
b1100 4
1'
b0 (
1#
#23200
0#
#23300
b1 (
1#
#23400
0#
#23500
b10 (
1#
#23600
0#
#23700
b11 (
1#
#23800
0#
#23900
b100 (
1#
#24000
0#
#24100
0'
b0 (
1#
#24200
0#
#24300
b1 (
1#
#24400
0#
#24500
b10 (
1#
#24600
0#
#24700
b11 (
1#
#24800
0#
#24900
b100 (
1#
#25000
0#
#25100
b1110 .
b11 2
b1001 3
b1101 *
b110 !
b110 &
b110 )
b110 4
b11 5
1'
b0 (
1#
#25200
0#
#25300
b1 (
1#
#25400
0#
#25500
b10 (
1#
#25600
0#
#25700
b11 (
1#
#25800
0#
#25900
b100 (
1#
#26000
0#
#26100
0'
b0 (
1#
#26200
0#
#26300
b1 (
1#
#26400
0#
#26500
b10 (
1#
#26600
0#
#26700
b11 (
1#
#26800
0#
#26900
b100 (
1#
#27000
0#
#27100
b1001 2
b1100 3
b1111 .
b1001 5
b1110 *
b11 !
b11 &
b11 )
b11 4
1'
b0 (
1#
#27200
0#
#27300
b1 (
1#
#27400
0#
#27500
b10 (
1#
#27600
0#
#27700
b11 (
1#
#27800
0#
#27900
b100 (
1#
#28000
0#
#28100
0'
b0 (
1#
#28200
0#
#28300
b1 (
1#
#28400
0#
#28500
b10 (
1#
#28600
0#
#28700
b11 (
1#
#28800
0#
#28900
b100 (
1#
#29000
0#
#29100
b10000 .
b1100 2
b110 3
b1111 *
b1001 !
b1001 &
b1001 )
b1001 4
b1100 5
1'
b0 (
1#
#29200
0#
#29300
b1 (
1#
#29400
0#
#29500
b10 (
1#
#29600
0#
#29700
b11 (
1#
#29800
0#
#29900
b100 (
1#
#30000
0#
#30100
0'
b0 (
1#
#30200
0#
#30300
b1 (
1#
#30400
0#
#30500
b10 (
1#
#30600
0#
#30700
b11 (
1#
#30800
0#
#30900
b100 (
1#
#31000
0#
#31100
b110 2
b11 3
b10001 .
b110 5
b10000 *
b1100 !
b1100 &
b1100 )
b1100 4
1'
b0 (
1#
#31200
0#
#31300
b1 (
1#
#31400
0#
#31500
b10 (
1#
#31600
0#
#31700
b11 (
1#
#31800
0#
#31900
b100 (
1#
#32000
0#
#32100
0'
b0 (
1#
#32200
0#
#32300
b1 (
1#
#32400
0#
#32500
b10 (
1#
#32600
0#
#32700
b11 (
1#
#32800
0#
#32900
b100 (
1#
#33000
0#
#33100
b10010 .
b11 2
b1001 3
b10001 *
b110 !
b110 &
b110 )
b110 4
b11 5
1'
b0 (
1#
#33200
0#
#33300
b1 (
1#
#33400
0#
#33500
b10 (
1#
#33600
0#
#33700
b11 (
1#
#33800
0#
#33900
b100 (
1#
#34000
0#
#34100
0'
b0 (
1#
#34200
0#
#34300
b1 (
1#
#34400
0#
#34500
b10 (
1#
#34600
0#
#34700
b11 (
1#
#34800
0#
#34900
b100 (
1#
#35000
0#
#35100
b1001 2
b1100 3
b10011 .
b1001 5
b10010 *
b11 !
b11 &
b11 )
b11 4
1'
b0 (
1#
#35200
0#
#35300
b1 (
1#
#35400
0#
#35500
b10 (
1#
#35600
0#
#35700
b11 (
1#
#35800
0#
#35900
b100 (
1#
#36000
0#
#36100
0'
b0 (
1#
#36200
0#
#36300
b1 (
1#
#36400
0#
#36500
b10 (
1#
#36600
0#
#36700
b11 (
1#
#36800
0#
#36900
b100 (
1#
#37000
0#
#37100
b10100 .
b1100 2
b110 3
b10011 *
b1001 !
b1001 &
b1001 )
b1001 4
b1100 5
1'
b0 (
1#
#37200
0#
#37300
b1 (
1#
#37400
0#
#37500
b10 (
1#
#37600
0#
#37700
b11 (
1#
#37800
0#
#37900
b100 (
1#
#38000
0#
#38100
0'
b0 (
1#
#38200
0#
#38300
b1 (
1#
#38400
0#
#38500
b10 (
1#
#38600
0#
#38700
b11 (
1#
#38800
0#
#38900
b100 (
1#
#39000
0#
#39100
b110 2
b11 3
b10101 .
b110 5
b10100 *
b1100 !
b1100 &
b1100 )
b1100 4
1'
b0 (
1#
#39200
0#
#39300
b1 (
1#
#39400
0#
#39500
b10 (
1#
#39600
0#
#39700
b11 (
1#
#39800
0#
#39900
b100 (
1#
#40000
0#
#40100
0'
b0 (
1#
#40200
0#
#40300
b1 (
1#
#40400
0#
#40500
b10 (
1#
#40600
0#
#40700
b11 (
1#
#40800
0#
#40900
b100 (
1#
#41000
0#
#41100
b10110 .
b11 2
b1001 3
b10101 *
b110 !
b110 &
b110 )
b110 4
b11 5
1'
b0 (
1#
#41200
0#
#41300
b1 (
1#
#41400
0#
#41500
b10 (
1#
#41600
0#
#41700
b11 (
1#
#41800
0#
#41900
b100 (
1#
#42000
0#
#42100
0'
b0 (
1#
#42200
0#
#42300
b1 (
1#
#42400
0#
#42500
b10 (
1#
#42600
0#
#42700
b11 (
1#
#42800
0#
#42900
b100 (
1#
#43000
0#
#43100
b1001 2
b1100 3
b10111 .
b1001 5
b10110 *
b11 !
b11 &
b11 )
b11 4
1'
b0 (
1#
#43200
0#
#43300
b1 (
1#
#43400
0#
#43500
b10 (
1#
#43600
0#
#43700
b11 (
1#
#43800
0#
#43900
b100 (
1#
#44000
0#
#44100
0'
b0 (
1#
#44200
0#
#44300
b1 (
1#
#44400
0#
#44500
b10 (
1#
#44600
0#
#44700
b11 (
1#
#44800
0#
#44900
b100 (
1#
#45000
0#
#45100
b11000 .
b1100 2
b110 3
b10111 *
b1001 !
b1001 &
b1001 )
b1001 4
b1100 5
1'
b0 (
1#
#45200
0#
#45300
b1 (
1#
#45400
0#
#45500
b10 (
1#
#45600
0#
#45700
b11 (
1#
#45800
0#
#45900
b100 (
1#
#46000
0#
#46100
0'
b0 (
1#
#46200
0#
#46300
b1 (
1#
#46400
0#
#46500
b10 (
1#
#46600
0#
#46700
b11 (
1#
#46800
0#
#46900
b100 (
1#
#47000
0#
#47100
b110 2
b11 3
b11001 .
b110 5
b11000 *
b1100 !
b1100 &
b1100 )
b1100 4
1'
b0 (
1#
#47200
0#
#47300
b1 (
1#
#47400
0#
#47500
b10 (
1#
#47600
0#
#47700
b11 (
1#
#47800
0#
#47900
b100 (
1#
#48000
0#
#48100
0'
b0 (
1#
#48200
0#
#48300
b1 (
1#
#48400
0#
#48500
b10 (
1#
#48600
0#
#48700
b11 (
1#
#48800
0#
#48900
b100 (
1#
#49000
0#
#49100
b11010 .
b11 2
b1001 3
b11001 *
b110 !
b110 &
b110 )
b110 4
b11 5
1'
b0 (
1#
#49200
0#
#49300
b1 (
1#
#49400
0#
#49500
b10 (
1#
#49600
0#
#49700
b11 (
1#
#49800
0#
#49900
b100 (
1#
#50000
0#
#50100
0'
b0 (
1#
#50200
0#
#50300
b1 (
1#
#50400
0#
#50500
b10 (
1#
#50600
0#
#50700
b11 (
1#
#50800
0#
#50900
b100 (
1#
#51000
0#
#51100
b1001 2
b1100 3
b11011 .
b1001 5
b11010 *
b11 !
b11 &
b11 )
b11 4
1'
b0 (
1#
#51200
0#
#51300
b1 (
1#
#51400
0#
#51500
b10 (
1#
#51600
0#
#51700
b11 (
1#
#51800
0#
#51900
b100 (
1#
#52000
0#
#52100
0'
b0 (
1#
#52200
0#
#52300
b1 (
1#
#52400
0#
#52500
b10 (
1#
#52600
0#
#52700
b11 (
1#
#52800
0#
#52900
b100 (
1#
#53000
0#
#53100
b11100 .
b1100 2
b110 3
b11011 *
b1001 !
b1001 &
b1001 )
b1001 4
b1100 5
1'
b0 (
1#
#53200
0#
#53300
b1 (
1#
#53400
0#
#53500
b10 (
1#
#53600
0#
#53700
b11 (
1#
#53800
0#
#53900
b100 (
1#
#54000
0#
#54100
0'
b0 (
1#
#54200
0#
#54300
b1 (
1#
#54400
0#
#54500
b10 (
1#
#54600
0#
#54700
b11 (
1#
#54800
0#
#54900
b100 (
1#
#55000
0#
#55100
b110 2
b11 3
b11101 .
b110 5
b11100 *
b1100 !
b1100 &
b1100 )
b1100 4
1'
b0 (
1#
#55200
0#
#55300
b1 (
1#
#55400
0#
#55500
b10 (
1#
#55600
0#
#55700
b11 (
1#
#55800
0#
#55900
b100 (
1#
#56000
0#
#56100
0'
b0 (
1#
#56200
0#
#56300
b1 (
1#
#56400
0#
#56500
b10 (
1#
#56600
0#
#56700
b11 (
1#
#56800
0#
#56900
b100 (
1#
#57000
0#
#57100
b11110 .
b11 2
b1001 3
b11101 *
b110 !
b110 &
b110 )
b110 4
b11 5
1'
b0 (
1#
#57200
0#
#57300
b1 (
1#
#57400
0#
#57500
b10 (
1#
#57600
0#
#57700
b11 (
1#
#57800
0#
#57900
b100 (
1#
#58000
0#
#58100
0'
b0 (
1#
#58200
0#
#58300
b1 (
1#
#58400
0#
#58500
b10 (
1#
#58600
0#
#58700
b11 (
1#
#58800
0#
#58900
b100 (
1#
#59000
0#
#59100
b1001 2
b1100 3
b11111 .
b1001 5
b11110 *
b11 !
b11 &
b11 )
b11 4
1'
b0 (
1#
#59200
0#
#59300
b1 (
1#
#59400
0#
#59500
b10 (
1#
#59600
0#
#59700
b11 (
1#
#59800
0#
#59900
b100 (
1#
#60000
0#
#60100
0'
b0 (
1#
#60200
0#
#60300
b1 (
1#
#60400
0#
#60500
b10 (
1#
#60600
0#
#60700
b11 (
1#
#60800
0#
#60900
b100 (
1#
#61000
0#
#61100
b100000 .
b1100 2
b110 3
b11111 *
b1001 !
b1001 &
b1001 )
b1001 4
b1100 5
1'
b0 (
1#
#61200
0#
#61300
b1 (
1#
#61400
0#
#61500
b10 (
1#
#61600
0#
#61700
b11 (
1#
#61800
0#
#61900
b100 (
1#
#62000
0#
#62100
0'
b0 (
1#
#62200
0#
#62300
b1 (
1#
#62400
0#
#62500
b10 (
1#
#62600
0#
#62700
b11 (
1#
#62800
0#
#62900
b100 (
1#
#63000
0#
#63100
b110 2
b11 3
b100001 .
b110 5
b100000 *
b1100 !
b1100 &
b1100 )
b1100 4
1'
b0 (
1#
#63200
0#
#63300
b1 (
1#
#63400
0#
#63500
b10 (
1#
#63600
0#
#63700
b11 (
1#
#63800
0#
#63900
b100 (
1#
#64000
0#
#64100
0'
b0 (
1#
#64200
0#
#64300
b1 (
1#
#64400
0#
#64500
b10 (
1#
#64600
0#
#64700
b11 (
1#
#64800
0#
#64900
b100 (
1#
#65000
0#
#65100
b100010 .
b11 2
b1001 3
b100001 *
b110 !
b110 &
b110 )
b110 4
b11 5
1'
b0 (
1#
#65200
0#
#65300
b1 (
1#
#65400
0#
#65500
b10 (
1#
#65600
0#
#65700
b11 (
1#
#65800
0#
#65900
b100 (
1#
#66000
0#
#66100
0'
b0 (
1#
#66200
0#
#66300
b1 (
1#
#66400
0#
#66500
b10 (
1#
#66600
0#
#66700
b11 (
1#
#66800
0#
#66900
b100 (
1#
#67000
0#
#67100
b1001 2
b1100 3
b100011 .
b1001 5
b100010 *
b11 !
b11 &
b11 )
b11 4
1'
b0 (
1#
#67200
0#
#67300
b1 (
1#
#67400
0#
#67500
b10 (
1#
#67600
0#
#67700
b11 (
1#
#67800
0#
#67900
b100 (
1#
#68000
0#
#68100
0'
b0 (
1#
#68200
0#
#68300
b1 (
1#
#68400
0#
#68500
b10 (
1#
#68600
0#
#68700
b11 (
1#
#68800
0#
#68900
b100 (
1#
#69000
0#
#69100
b100100 .
b1100 2
b110 3
b100011 *
b1001 !
b1001 &
b1001 )
b1001 4
b1100 5
1'
b0 (
1#
#69200
0#
#69300
b1 (
1#
#69400
0#
#69500
b10 (
1#
#69600
0#
#69700
b11 (
1#
#69800
0#
#69900
b100 (
1#
#70000
0#
#70100
0'
b0 (
1#
#70200
0#
#70300
b1 (
1#
#70400
0#
#70500
b10 (
1#
#70600
0#
#70700
b11 (
1#
#70800
0#
#70900
b100 (
1#
#71000
0#
#71100
b110 2
b11 3
b100101 .
b110 5
b100100 *
b1100 !
b1100 &
b1100 )
b1100 4
1'
b0 (
1#
#71200
0#
#71300
b1 (
1#
#71400
0#
#71500
b10 (
1#
#71600
0#
#71700
b11 (
1#
#71800
0#
#71900
b100 (
1#
#72000
0#
#72100
0'
b0 (
1#
#72200
0#
#72300
b1 (
1#
#72400
0#
#72500
b10 (
1#
#72600
0#
#72700
b11 (
1#
#72800
0#
#72900
b100 (
1#
#73000
0#
#73100
b100110 .
b11 2
b1001 3
b100101 *
b110 !
b110 &
b110 )
b110 4
b11 5
1'
b0 (
1#
#73200
0#
#73300
b1 (
1#
#73400
0#
#73500
b10 (
1#
#73600
0#
#73700
b11 (
1#
#73800
0#
#73900
b100 (
1#
#74000
0#
#74100
0'
b0 (
1#
#74200
0#
#74300
b1 (
1#
#74400
0#
#74500
b10 (
1#
#74600
0#
#74700
b11 (
1#
#74800
0#
#74900
b100 (
1#
#75000
0#
#75100
b1001 2
b1100 3
b100111 .
b1001 5
b100110 *
b11 !
b11 &
b11 )
b11 4
1'
b0 (
1#
#75200
0#
#75300
b1 (
1#
#75400
0#
#75500
b10 (
1#
#75600
0#
#75700
b11 (
1#
#75800
0#
#75900
b100 (
1#
#76000
0#
#76100
0'
b0 (
1#
#76200
0#
#76300
b1 (
1#
#76400
0#
#76500
b10 (
1#
#76600
0#
#76700
b11 (
1#
#76800
0#
#76900
b100 (
1#
#77000
0#
#77100
b101000 .
b1100 2
b110 3
b100111 *
b1001 !
b1001 &
b1001 )
b1001 4
b1100 5
1'
b0 (
1#
#77200
0#
#77300
b1 (
1#
#77400
0#
#77500
b10 (
1#
#77600
0#
#77700
b11 (
1#
#77800
0#
#77900
b100 (
1#
#78000
0#
#78100
0'
b0 (
1#
#78200
0#
#78300
b1 (
1#
#78400
0#
#78500
b10 (
1#
#78600
0#
#78700
b11 (
1#
#78800
0#
#78900
b100 (
1#
#79000
0#
#79100
b110 2
b11 3
b101001 .
b110 5
b101000 *
b1100 !
b1100 &
b1100 )
b1100 4
1'
b0 (
1#
#79200
0#
#79300
b1 (
1#
#79400
0#
#79500
b10 (
1#
#79600
0#
#79700
b11 (
1#
#79800
0#
#79900
b100 (
1#
#80000
0#
#80100
0'
b0 (
1#
#80200
0#
#80300
b1 (
1#
#80400
0#
#80500
b10 (
1#
#80600
0#
#80700
b11 (
1#
#80800
0#
#80900
b100 (
1#
#81000
0#
#81100
b101010 .
b11 2
b1001 3
b101001 *
b110 !
b110 &
b110 )
b110 4
b11 5
1'
b0 (
1#
#81200
0#
#81300
b1 (
1#
#81400
0#
#81500
b10 (
1#
#81600
0#
#81700
b11 (
1#
#81800
0#
#81900
b100 (
1#
#82000
0#
#82100
0'
b0 (
1#
#82200
0#
#82300
b1 (
1#
#82400
0#
#82500
b10 (
1#
#82600
0#
#82700
b11 (
1#
#82800
0#
#82900
b100 (
1#
#83000
0#
#83100
b1001 2
b1100 3
b101011 .
b1001 5
b101010 *
b11 !
b11 &
b11 )
b11 4
1'
b0 (
1#
#83200
0#
#83300
b1 (
1#
#83400
0#
#83500
b10 (
1#
#83600
0#
#83700
b11 (
1#
#83800
0#
#83900
b100 (
1#
#84000
0#
#84100
0'
b0 (
1#
#84200
0#
#84300
b1 (
1#
#84400
0#
#84500
b10 (
1#
#84600
0#
#84700
b11 (
1#
#84800
0#
#84900
b100 (
1#
#85000
0#
#85100
b101100 .
b1100 2
b110 3
b101011 *
b1001 !
b1001 &
b1001 )
b1001 4
b1100 5
1'
b0 (
1#
#85200
0#
#85300
b1 (
1#
#85400
0#
#85500
b10 (
1#
#85600
0#
#85700
b11 (
1#
